ug4py_plugins_ijkdata-0.0.3.dist-info/RECORD
ug4py_plugins_ijkdata-0.0.3.dist-info/WHEEL
ug4py_plugins_ijkdata-0.0.3.dist-info/METADATA
ug4py/pyijkdata.cpython-312-darwin.so
