Metadata-Version: 2.2
Name: ug4py-plugins-ijkdata
Version: 0.0.3
Summary: This is UG4-plugin for ijkdata.
